{
  "title": "Light absorption / emission",
  "publicationStatus": "draft",
  "subtitle": "Absorption & Emission of Photons",
   "aboutOnLoad": true,
  "about": [
    "Discover what happens when a particular frequency of light is absorbed by an atom.",
    "",
    "Press the **Play** button.",
    "Change the **Energy of monochromatic light source** slider to see photons at different energy levels. ",
    "To make sure you see all the wavelengths [or photons], select the slider and use the arrow keys to ",
    "step through each wavelength.",
    "Wait for at least three series of a photon before moving to a different wavelength.",
    "The atoms will either absorb or let pass photons of each frequency.",
    "",
    "Which frequency of light is absorbed and re-emitted by these atoms?",
    "How does the model represent this?"
    ],
  "aspectRatio": 1.4,
  "fontScale": 0.95,
  "theme": [
    "has",
    "standalone-playback",
    "no-slider-bar"
  ],
  "models": [
    {
      "type": "md2d",
      "id": "elementA",
      "url": "models-converted/lab-version/1/md2d/space/light-absorption-emission/HASlight$0.json",
      "viewOptions": {
        "controlButtons": "play_reset",
        "backgroundColor": "#fff"
      },
      "modelOptions": {
        "timeStep": 3,
        "timeStepsPerTick": 5
      },
      "onLoad": [
        "setElementProperties(3, {epsilon: 0});",
        "setLightSourceNumber(4);"
      ]
    }
  ],
  "parameters": [
    {
      "name": "lightSourceFrequency",
      "initialValue": 1.725,
      "onChange": "setLightSourceFrequency(value);"
    },
    {
      "name": "lightSourceIntensity",
      "initialValue": 0,
      "onChange": "setLightSourcePeriod(600 - value);"
    }
  ],
  "components": [
    {
      "id": "playback",
      "type": "playback"
    },
    {
      "type": "slider",
      "id": "light-source-frequency",
      "min": 4.8,
      "max": 12.6,
      "steps": 17,
      "labels": [
        {
          "value": 5.4,
          "label": "Infrared"
        },
        {
          "value": 11.8,
          "label": "Ultraviolet"
        }
      ],
      "property": "lightSourceFrequency",
      "title": "Energy of monochromatic light source"
    },
    {
      "type": "slider",
      "id": "light-source-intensity",
      "min": 0,
      "max": 200,
      "steps": 50,
      "labels": [
        {
          "value": 20,
          "label": "Weak"
        },
        {
          "value": 175,
          "label": "Strong"
        }
      ],
      "property": "lightSourceIntensity",
      "title": "Intensity of light source"
    }
  ]
}
